batch_niistats/__init__.py
batch_niistats/cli.py
batch_niistats/modules/nii.py
batch_niistats/modules/utils.py
batch_niistats-1.0.2.dist-info/licenses/LICENSE
batch_niistats-1.0.2.dist-info/METADATA
batch_niistats-1.0.2.dist-info/WHEEL
batch_niistats-1.0.2.dist-info/entry_points.txt
batch_niistats-1.0.2.dist-info/top_level.txt
batch_niistats-1.0.2.dist-info/RECORD
